biaslyze/__init__.py
biaslyze/_plotly_dashboard.py
biaslyze/_plotting.py
biaslyze/augmentors.py
biaslyze/bias_detectors/__init__.py
biaslyze/bias_detectors/counterfactual_biasdetector.py
biaslyze/bias_detectors/lime_biasdetector.py
biaslyze/concept_class.py
biaslyze/concept_detectors.py
biaslyze/concepts/__init__
biaslyze/concepts/concepts_de.py
biaslyze/concepts/concepts_en.py
biaslyze/results/__init__.py
biaslyze/results/counterfactual_detection_results.py
biaslyze/results/lime_detection_results.py
biaslyze/text_representation.py
biaslyze/utils.py
biaslyze-0.1.0.dist-info/LICENSE
biaslyze-0.1.0.dist-info/METADATA
biaslyze-0.1.0.dist-info/WHEEL
biaslyze-0.1.0.dist-info/RECORD
