Metadata-Version: 2.1
Name: biaslyze
Version: 0.1.0
Summary: The NLP Bias Identification Toolkit
Home-page: https://biaslyze.org
License: BSD-3-Clause
Keywords: NLP,bias,ethics,fairness
Author: Tobias Sterbak & Stina Lohmüller
Author-email: hello@biaslyze.org
Maintainer: Tobias Sterbak
Maintainer-email: hello@tobiassterbak.com
Requires-Python: >=3.10,<3.11
Classifier: License :: OSI Approved :: BSD License
Classifier: Programming Language :: Python :: 3
Classifier: Programming Language :: Python :: 3.10
Classifier: Topic :: Scientific/Engineering :: Artificial Intelligence
Classifier: Topic :: Software Development :: Libraries :: Python Modules
Requires-Dist: dash (>=2.11.1,<3.0.0)
Requires-Dist: dill (>=0.3.7,<0.4.0)
Requires-Dist: jupyterlab (>=3.5.2,<4.0.0)
Requires-Dist: loguru (>=0.6.0,<0.7.0)
Requires-Dist: matplotlib (>=3.7.1,<4.0.0)
Requires-Dist: numpy (>=1.25.0)
Requires-Dist: pandas (>=1.5.3,<2.0.0)
Requires-Dist: plotly (>=5.15.0,<6.0.0)
Requires-Dist: scikit-learn (>=1.2.0,<2.0.0)
Requires-Dist: scipy (>=1.11.1,<2.0.0)
Requires-Dist: spacy (>=3.5.0,<4.0.0)
Project-URL: Repository, https://github.com/biaslyze-dev/biaslyze/issues
